Workbook

Sheet Instrucciones
A1: ISO 27001:2022 + ISO 31000 — SGSI Toolkit
A2: Herramientas de implementación: Contexto · Activos · Riesgos · Tratamiento · SoA | Los colores se actualizan automáticamente
A3: ISO/IEC 27001:2022 + ISO 31000:2018 + ISO/IEC 27005:2022 | Versión 2.0
B5: HOJA | C5: CONTENIDO
B6: 1-Contexto | C6: Cláusula 4: factores internos/externos, partes interesadas, alcance del SGSI
B7: 2-Inventario Activos | C7: Activos de información por categoría con valoración C/I/D automática — colores dinámicos
B8: 3-Identif Riesgos | C8: Tripla Activo / Amenaza / Vulnerabilidad según ISO 31000 §6.4.2
B9: 4-Matriz Riesgos | C9: Evaluación Probabilidad × Impacto (1-5) — colores y niveles automáticos al cambiar valores
B10: 5-Plan Tratamiento | C10: Opciones Mitigar/Evitar/Transferir/Aceptar con semáforo automático por estado
B11: 6-SoA Anexo A | C11: 93 controles completos Anexo A 2022 — colores automáticos por ¿Aplica? y Madurez
B12: 7-Dashboard | C12: KPIs y conteos automáticos que se actualizan al completar el resto de hojas
B14: LÓGICA DE COLORES (automática en todas las hojas)
B15: 🔴 CRÍTICO / NO IMPLEMENTADO | C15: Nivel riesgo ≥16 · Activo valor ≥8 · Estado 'No implementado' · ❌ en SoA
B16: 🟠 ALTO / EN PROCESO | C16: Nivel riesgo 11-15 · Valor activo 6-7 · '⚠️ En proceso' · 'MITIGAR'
B17: 🟡 MEDIO / PARCIAL | C17: Nivel riesgo 6-10 · '⚠️ PARCIAL' · 'En implementación'
B18: 🟢 BAJO / IMPLEMENTADO | C18: Nivel riesgo 1-5 · Activo valor ≤5 · '✅ CUMPLE' · 'Implementado y verificado'
B20: INSTRUCCIONES DE USO
B21: 1. Empezar por hoja 1-Contexto: completar las celdas amarillas
B22: 2. Cargar todos los activos en 2-Inventario — ajustar C, I, D (1-3)
B23: 3. Completar la tripla en 3-Identif Riesgos
B24: 4. En 4-Matriz: ajustar Probabilidad (1-5) e Impacto (1-5) — el nivel y color cambian solos
B25: 5. En 5-Plan Tratamiento: seleccionar tratamiento del desplegable
B26: 6. En 6-SoA: marcar ¿Aplica? y Madurez con los desplegables de cada fila
B27: 7. Ver Dashboard para resumen ejecutivo

Sheet 1-Contexto
A1: CONTEXTO DE LA ORGANIZACIÓN — Cláusula 4 ISO 27001:2022
A2: 4.1 Factores internos y externos | 4.2 Partes interesadas | 4.3 Alcance del SGSI
A3: Contexto — Cláusula 4
B5: 4.1 FACTORES INTERNOS
B6: Categoría | C6: Descripción | D6: Impacto en SGSI | E6: Notas (editar)
B7: Estructura organizacional | C7: Tamaño, áreas, niveles jerárquicos y modelo de gobierno
B8: Cultura organizacional | C8: Nivel de madurez en seguridad, tolerancia al riesgo
B9: Procesos de negocio core | C9: Procesos críticos y dependencias operativas
B10: Infraestructura tecnológica | C10: Arquitectura, cloud vs on-premise, sistemas legados
B11: Recursos y capacidades | C11: Presupuesto, personal especializado, herramientas
B12: Objetivos estratégicos | C12: Visión, misión y metas de mediano plazo
B13: Activos críticos de información | C13: Qué información es vital para la operación
B16: 4.1 FACTORES EXTERNOS
B17: Categoría | C17: Descripción | D17: Impacto en SGSI | E17: Notas (editar)
B18: Marco legal y regulatorio | C18: Leyes de protección de datos, regulación sectorial
B19: Entorno competitivo | C19: Estándares de seguridad exigidos por el mercado
B20: Amenazas del sector | C20: Tipo de ciberataques frecuentes en la industria
B21: Cadena de suministro | C21: Dependencia de proveedores tecnológicos críticos
B22: Tendencias tecnológicas | C22: IA, cloud, trabajo remoto, IoT, APIs
B23: Factores sociopolíticos | C23: Estabilidad regulatoria, geopolítica de datos
B26: 4.2 PARTES INTERESADAS — NECESIDADES Y EXPECTATIVAS
B27: Parte interesada | C27: Necesidades / Expectativas | D27: Requisito para el SGSI | E27: Notas (editar)
B28: Clientes / Usuarios | C28: Confidencialidad, disponibilidad, cumplimiento normativo
B29: Empleados | C29: Claridad en políticas, capacitación, protección de sus datos
B30: Accionistas / Directorio | C30: Continuidad del negocio, reputación, reducción de riesgo
B31: Reguladores / Autoridades | C31: Cumplimiento legal, notificación de incidentes
B32: Proveedores / Socios | C32: Acuerdos de confidencialidad, accesos compartidos
B33: Auditores | C33: Evidencia de controles, trazabilidad, registros
B36: 4.3 ALCANCE DEL SGSI (completar la declaración formal)
B37: Escribir aquí la declaración de alcance: qué procesos, sistemas, ubicaciones y personal están incluidos. Indicar exclusiones justificadas.

Sheet 2-Inventario Activos
A1: INVENTARIO DE ACTIVOS — Anexo A 5.9 ISO 27001:2022
A2: Información · Software · Hardware · Servicios · Personas | Valoración CID | Colores automáticos al cambiar valores
A3: Inventario de Activos
A5: # | B5: ID | C5: Activo | D5: Tipo | E5: Propietario | F5: C | G5: I | H5: D | I5: Valor (C+I+D) | J5: Criticidad (automático) | K5: Ubicación / Sistema | L5: Estado ▼
A6: 1 | B6: AC-01 | C6: Base de datos de clientes/pacientes | D6: Información | E6: Gerencia Operaciones | F6: 1 | G6: 1 | H6: 1 | I6: =F6+G6+H6 -> 3 | J6: =IF(I6>=8,"CRITICO",IF(I6>=6,"IMPORTANTE","NORMAL")) -> NORMAL | K6: Servidor / Cloud AWS | L6: En revisión
A7: 2 | B7: AC-02 | C7: Datos personales de empleados | D7: Información | E7: RRHH | F7: 3 | G7: 3 | H7: 2 | I7: =F7+G7+H7 -> 8 | J7: =IF(I7>=8,"CRITICO",IF(I7>=6,"IMPORTANTE","NORMAL")) -> CRITICO | K7: Sistema RRHH / HRIS | L7: Activo
A8: 3 | B8: AC-03 | C8: Código fuente de aplicaciones | D8: Información / Software | E8: Tecnología | F8: 3 | G8: 3 | H8: 2 | I8: =F8+G8+H8 -> 8 | J8: =IF(I8>=8,"CRITICO",IF(I8>=6,"IMPORTANTE","NORMAL")) -> CRITICO | K8: GitHub / GitLab | L8: Activo
A9: 4 | B9: AC-04 | C9: Contratos y documentación legal | D9: Información | E9: Legal / Administración | F9: 3 | G9: 3 | H9: 2 | I9: =F9+G9+H9 -> 8 | J9: =IF(I9>=8,"CRITICO",IF(I9>=6,"IMPORTANTE","NORMAL")) -> CRITICO | K9: Repositorio documental | L9: Activo
A10: 5 | B10: AC-05 | C10: Registros financieros y facturación | D10: Información | E10: Administración | F10: 3 | G10: 3 | H10: 2 | I10: =F10+G10+H10 -> 8 | J10: =IF(I10>=8,"CRITICO",IF(I10>=6,"IMPORTANTE","NORMAL")) -> CRITICO | K10: ERP / Sistema contable | L10: Activo
A11: 6 | B11: AC-06 | C11: Aplicación web principal | D11: Software | E11: Tecnología | F11: 2 | G11: 3 | H11: 3 | I11: =F11+G11+H11 -> 8 | J11: =IF(I11>=8,"CRITICO",IF(I11>=6,"IMPORTANTE","NORMAL")) -> CRITICO | K11: AWS — Producción | L11: Activo
A12: 7 | B12: AC-07 | C12: Aplicación móvil | D12: Software | E12: Tecnología | F12: 2 | G12: 3 | H12: 3 | I12: =F12+G12+H12 -> 8 | J12: =IF(I12>=8,"CRITICO",IF(I12>=6,"IMPORTANTE","NORMAL")) -> CRITICO | K12: App Store / Play Store | L12: Activo
A13: 8 | B13: AC-08 | C13: Sistema CRM | D13: Software | E13: Comercial | F13: 2 | G13: 2 | H13: 2 | I13: =F13+G13+H13 -> 6 | J13: =IF(I13>=8,"CRITICO",IF(I13>=6,"IMPORTANTE","NORMAL")) -> IMPORTANTE | K13: Cloud SaaS | L13: Activo
A14: 9 | B14: AC-09 | C14: Sistema de mesa de ayuda (ticketing) | D14: Software | E14: Atención al Cliente | F14: 2 | G14: 2 | H14: 2 | I14: =F14+G14+H14 -> 6 | J14: =IF(I14>=8,"CRITICO",IF(I14>=6,"IMPORTANTE","NORMAL")) -> IMPORTANTE | K14: Cloud SaaS | L14: Activo
A15: 10 | B15: AC-10 | C15: Suite de productividad (Google/M365) | D15: Software / Servicio | E15: Tecnología | F15: 3 | G15: 2 | H15: 3 | I15: =F15+G15+H15 -> 8 | J15: =IF(I15>=8,"CRITICO",IF(I15>=6,"IMPORTANTE","NORMAL")) -> CRITICO | K15: Cloud | L15: Activo
A16: 11 | B16: AC-11 | C16: Laptops corporativas | D16: Hardware | E16: Tecnología / RRHH | F16: 3 | G16: 2 | H16: 2 | I16: =F16+G16+H16 -> 7 | J16: =IF(I16>=8,"CRITICO",IF(I16>=6,"IMPORTANTE","NORMAL")) -> IMPORTANTE | K16: Equipos asignados a empleados | L16: Activo
A17: 12 | B17: AC-12 | C17: Servidores / infraestructura on-premise | D17: Hardware | E17: Tecnología | F17: 3 | G17: 3 | H17: 3 | I17: =F17+G17+H17 -> 9 | J17: =IF(I17>=8,"CRITICO",IF(I17>=6,"IMPORTANTE","NORMAL")) -> CRITICO | K17: Datacenter / Oficina | L17: Activo
... A25: 20 | B25: AC-20 | C25: Personal con acceso a datos sensibles | D25: Personas | E25: Áreas operativas | F25: 3 | G25: 3 | H25: 2 | I25: =F25+G25+H25 -> 8 | J25: =IF(I25>=8,"CRITICO",IF(I25>=6,"IMPORTANTE","NORMAL")) -> CRITICO | K25: Interno | L25: Activo
B26: 📐 C/I/D: 1=Bajo 2=Medio 3=Alto | Valor=C+I+D (máx 9) | Criticidad se calcula sola | Los colores de Valor y Criticidad cambian automáticamente al editar C, I o D

Sheet 3-Identif Riesgos
A1: IDENTIFICACIÓN DE RIESGOS — Activo / Amenaza / Vulnerabilidad
A2: ISO 31000 §6.4.2 + ISO/IEC 27005 | Tripla de identificación | Completar celdas amarillas con nuevos riesgos
A3: Identificación de Riesgos
A5: # | B5: ID | C5: Activo crítico afectado | D5: Amenaza identificada | E5: Vulnerabilidad explotada | F5: Origen ▼
A6: 1 | B6: R-01 | C6: Base de datos de clientes/pacientes | D6: Acceso no autorizado / exfiltración de datos | E6: MFA no implementado universalmente; gestión de accesos informal | F6: Interno
A7: 2 | B7: R-02 | C7: Infraestructura cloud (AWS/Azure) | D7: Ransomware con cifrado de datos y caída del servicio | E7: Backups sin pruebas de restauración; sin plan de continuidad (BCP) | F7: Externo
A8: 3 | B8: R-03 | C8: Suite de productividad — correo | D8: Phishing / Business Email Compromise (BEC) | E8: Capacitación esporádica; sin filtros DMARC/DKIM/SPF configurados | F8: Externo
A9: 4 | B9: R-04 | C9: Aplicación web principal | D9: Inyección SQL / XSS / explotación OWASP Top 10 | E9: Sin revisiones de seguridad de código (SAST/DAST) en el SDLC | F9: Externo
A10: 5 | B10: R-05 | C10: Código fuente (repositorios Git) | D10: Robo o manipulación de código / inyección de malware | E10: Accesos sin revisión periódica; sin ramas protegidas (branch rules) | F10: Interno/Externo
A11: 6 | B11: R-06 | C11: Aplicación móvil de campo | D11: Robo de credenciales / sesión no autorizada | E11: Sin MFA en la app; tokens de sesión con vida útil extendida | F11: Externo
A12: 7 | B12: R-07 | C12: Conectividad VPN / acceso remoto | D12: Interceptación de comunicaciones (Man-in-the-Middle) | E12: Sin política formal de acceso remoto; dispositivos BYOD sin control | F12: Externo
A13: 8 | B13: R-08 | C13: Registros financieros y facturación | D13: Fraude interno / manipulación de datos financieros | E13: Sin separación de funciones; sin auditoría de logs de acceso | F13: Interno
A14: 9 | B14: R-09 | C14: Equipo de Tecnología / personal clave | D14: Pérdida de personal crítico / fuga de conocimiento | E14: Sin gestión de conocimiento documentada; sin offboarding formal | F14: Interno
A15: 10 | B15: R-10 | C15: Laptops corporativas | D15: Robo o pérdida de equipo con datos sin cifrar | E15: Sin cifrado de disco obligatorio (BitLocker/FileVault); sin MDM | F15: Externo
A16: 11 | B16: R-11 | C16: Servidores on-premise | D16: Falla de hardware / corte de energía prolongado | E16: Sin redundancia (UPS/generador); sin contrato de mantenimiento | F16: Ambiental
A17: 12 | B17: R-12 | C17: Datos personales de empleados | D17: Fuga de datos laborales sensibles por acceso indebido | E17: Sin clasificación de información; controles de acceso deficientes | F17: Interno

Sheet 4-Matriz Riesgos
A1: MATRIZ DE EVALUACIÓN DE RIESGOS — Probabilidad × Impacto (1-5)
A2: ISO 31000 §6.4.3-6.4.4 | Escala 5×5 (máximo 25) | Nivel y color se actualizan automáticamente al cambiar P o I
A3: Matriz de Evaluación
A5: # | B5: ID | C5: Riesgo / Escenario | D5: Activo afectado | E5: Prob. (1-5) ▼ | F5: Imp. (1-5) ▼ | G5: Nivel P×I | H5: Categoría (automático) | I5: Tratamiento (automático)
A6: 1 | B6: R-01 | C6: Exfiltración de datos por acceso no autorizado | D6: BD clientes/pacientes | E6: 2 | F6: 5 | G6: =E6*F6 -> 10 | H6: =IF(G6>=16,"CRITICO",IF(G6>=11,"ALTO",IF(G6>=6,"MEDIO","BAJO"))) -> MEDIO | I6: =IF(G6>=16,"MITIGAR / EVITAR",IF(G6>=11,"MITIGAR",IF(G6>=6,"MITIGAR / TRANSFERIR","ACEPTAR"))) -> MITIGAR / TRANSFERIR
A7: 2 | B7: R-02 | C7: Ransomware con cifrado de datos en cloud | D7: Infraestructura cloud | E7: 4 | F7: 5 | G7: =E7*F7 -> 20 | H7: =IF(G7>=16,"CRITICO",IF(G7>=11,"ALTO",IF(G7>=6,"MEDIO","BAJO"))) -> CRITICO | I7: =IF(G7>=16,"MITIGAR / EVITAR",IF(G7>=11,"MITIGAR",IF(G7>=6,"MITIGAR / TRANSFERIR","ACEPTAR"))) -> MITIGAR / EVITAR
A8: 3 | B8: R-03 | C8: Compromiso de cuenta corporativa por phishing/BEC | D8: Correo corporativo | E8: 4 | F8: 4 | G8: =E8*F8 -> 16 | H8: =IF(G8>=16,"CRITICO",IF(G8>=11,"ALTO",IF(G8>=6,"MEDIO","BAJO"))) -> CRITICO | I8: =IF(G8>=16,"MITIGAR / EVITAR",IF(G8>=11,"MITIGAR",IF(G8>=6,"MITIGAR / TRANSFERIR","ACEPTAR"))) -> MITIGAR / EVITAR
A9: 4 | B9: R-04 | C9: Inyección SQL/XSS en plataforma web | D9: App web principal | E9: 3 | F9: 4 | G9: =E9*F9 -> 12 | H9: =IF(G9>=16,"CRITICO",IF(G9>=11,"ALTO",IF(G9>=6,"MEDIO","BAJO"))) -> ALTO | I9: =IF(G9>=16,"MITIGAR / EVITAR",IF(G9>=11,"MITIGAR",IF(G9>=6,"MITIGAR / TRANSFERIR","ACEPTAR"))) -> MITIGAR
A10: 5 | B10: R-05 | C10: Robo de código fuente con inyección de malware | D10: Repositorios Git | E10: 2 | F10: 4 | G10: =E10*F10 -> 8 | H10: =IF(G10>=16,"CRITICO",IF(G10>=11,"ALTO",IF(G10>=6,"MEDIO","BAJO"))) -> MEDIO | I10: =IF(G10>=16,"MITIGAR / EVITAR",IF(G10>=11,"MITIGAR",IF(G10>=6,"MITIGAR / TRANSFERIR","ACEPTAR"))) -> MITIGAR / TRANSFERIR
A11: 6 | B11: R-06 | C11: Robo de credenciales en app móvil sin MFA | D11: App móvil | E11: 3 | F11: 4 | G11: =E11*F11 -> 12 | H11: =IF(G11>=16,"CRITICO",IF(G11>=11,"ALTO",IF(G11>=6,"MEDIO","BAJO"))) -> ALTO | I11: =IF(G11>=16,"MITIGAR / EVITAR",IF(G11>=11,"MITIGAR",IF(G11>=6,"MITIGAR / TRANSFERIR","ACEPTAR"))) -> MITIGAR
A12: 7 | B12: R-07 | C12: Interceptación de comunicaciones vía VPN | D12: VPN / Acceso remoto | E12: 3 | F12: 3 | G12: =E12*F12 -> 9 | H12: =IF(G12>=16,"CRITICO",IF(G12>=11,"ALTO",IF(G12>=6,"MEDIO","BAJO"))) -> MEDIO | I12: =IF(G12>=16,"MITIGAR / EVITAR",IF(G12>=11,"MITIGAR",IF(G12>=6,"MITIGAR / TRANSFERIR","ACEPTAR"))) -> MITIGAR / TRANSFERIR
A13: 8 | B13: R-08 | C13: Fraude interno sobre datos financieros | D13: Registros financieros | E13: 2 | F13: 4 | G13: =E13*F13 -> 8 | H13: =IF(G13>=16,"CRITICO",IF(G13>=11,"ALTO",IF(G13>=6,"MEDIO","BAJO"))) -> MEDIO | I13: =IF(G13>=16,"MITIGAR / EVITAR",IF(G13>=11,"MITIGAR",IF(G13>=6,"MITIGAR / TRANSFERIR","ACEPTAR"))) -> MITIGAR / TRANSFERIR
A14: 9 | B14: R-09 | C14: Pérdida de personal clave sin documentación | D14: Equipo Tecnología | E14: 3 | F14: 3 | G14: =E14*F14 -> 9 | H14: =IF(G14>=16,"CRITICO",IF(G14>=11,"ALTO",IF(G14>=6,"MEDIO","BAJO"))) -> MEDIO | I14: =IF(G14>=16,"MITIGAR / EVITAR",IF(G14>=11,"MITIGAR",IF(G14>=6,"MITIGAR / TRANSFERIR","ACEPTAR"))) -> MITIGAR / TRANSFERIR
A15: 10 | B15: R-10 | C15: Robo/pérdida de laptop sin cifrado | D15: Laptops corporativas | E15: 3 | F15: 3 | G15: =E15*F15 -> 9 | H15: =IF(G15>=16,"CRITICO",IF(G15>=11,"ALTO",IF(G15>=6,"MEDIO","BAJO"))) -> MEDIO | I15: =IF(G15>=16,"MITIGAR / EVITAR",IF(G15>=11,"MITIGAR",IF(G15>=6,"MITIGAR / TRANSFERIR","ACEPTAR"))) -> MITIGAR / TRANSFERIR
A16: 11 | B16: R-11 | C16: Falla de hardware / corte prolongado de energía | D16: Servidores on-premise | E16: 2 | F16: 3 | G16: =E16*F16 -> 6 | H16: =IF(G16>=16,"CRITICO",IF(G16>=11,"ALTO",IF(G16>=6,"MEDIO","BAJO"))) -> MEDIO | I16: =IF(G16>=16,"MITIGAR / EVITAR",IF(G16>=11,"MITIGAR",IF(G16>=6,"MITIGAR / TRANSFERIR","ACEPTAR"))) -> MITIGAR / TRANSFERIR
A17: 12 | B17: R-12 | C17: Fuga de datos personales de empleados | D17: Datos personales empleados | E17: 3 | F17: 4 | G17: =E17*F17 -> 12 | H17: =IF(G17>=16,"CRITICO",IF(G17>=11,"ALTO",IF(G17>=6,"MEDIO","BAJO"))) -> ALTO | I17: =IF(G17>=16,"MITIGAR / EVITAR",IF(G17>=11,"MITIGAR",IF(G17>=6,"MITIGAR / TRANSFERIR","ACEPTAR"))) -> MITIGAR
B20: 🗺 MAPA DE CALOR — Referencia visual Probabilidad × Impacto
B21: Imp ▼ / Prob ► | C21: P=1 | D21: P=2 | E21: P=3 | F21: P=4 | G21: P=5
B22: I=5 | C22: 5 | D22: 10 | E22: 15 | F22: 20 | G22: 25
B23: I=4 | C23: 4 | D23: 8 | E23: 12 | F23: 16 | G23: 20
B24: I=3 | C24: 3 | D24: 6 | E24: 9 | F24: 12 | G24: 15
B25: I=2 | C25: 2 | D25: 4 | E25: 6 | F25: 8 | G25: 10
B26: I=1 | C26: 1 | D26: 2 | E26: 3 | F26: 4 | G26: 5
B28: Bajo 1-5 | D28: Medio 6-10 | F28: Alto 11-15 | H28: Crítico 16-25

Sheet 5-Plan Tratamiento
A1: PLAN DE TRATAMIENTO DE RIESGOS
A2: ISO 31000 §6.5 | Opciones: Mitigar · Evitar · Transferir · Aceptar | Colores automáticos al seleccionar opción
A3: Plan de Tratamiento
A5: # | B5: ID | C5: Riesgo | D5: Tratamiento ▼ | E5: Acción concreta / Justificación | F5: Responsable | G5: Fecha obj. | H5: Estado ▼
A6: 1 | B6: R-01 | C6: Exfiltración de datos por acceso no autorizado | D6: MITIGAR | E6: Implementar MFA obligatorio, RBAC, cifrado en reposo/tránsito. Riesgo crítico — reducción activa es la única opción razonable. | F6: CISO / Tecnología | G6: Q1 | H6: ✅ Completado
A7: 2 | B7: R-02 | C7: Ransomware en infraestructura cloud | D7: MITIGAR | E7: Política backups 3-2-1 con pruebas de restauración + segmentación de red + BCP/DRP documentado y probado. | F7: Tecnología | G7: Q1 | H7: ⚠️ En proceso
A8: 3 | B8: R-03 | C8: Compromiso de cuenta por phishing / BEC | D8: MITIGAR | E8: MFA en correo, DMARC/DKIM/SPF, simulaciones de phishing, capacitación continua (no solo anual). | F8: CISO / RRHH | G8: Q1 | H8: 🔲 Pendiente
A9: 4 | B9: R-04 | C9: Inyección SQL/XSS en app web | D9: MITIGAR | E9: Integrar SAST/DAST en CI/CD, adoptar OWASP ASVS como estándar, pentesting externo anual. | F9: Tecnología | G9: Q2 | H9: 🔲 Pendiente
A10: 5 | B10: R-05 | C10: Robo de código fuente / malware en repo | D10: MITIGAR | E10: Ramas protegidas, PR obligatorio con revisión, SCA (Dependabot), MFA en GitHub/GitLab. | F10: Tecnología | G10: Q2 | H10: 🔲 Pendiente
A11: 6 | B11: R-06 | C11: Robo de credenciales en app móvil | D11: MITIGAR | E11: MFA en la app, tokens con expiración reducida, detección de comportamiento anómalo. | F11: Tecnología | G11: Q2 | H11: 🔲 Pendiente
A12: 7 | B12: R-07 | C12: Interceptación de comunicaciones VPN | D12: MITIGAR | E12: Política formal de acceso remoto, VPN corporativa con cifrado actualizado, evaluar Zero Trust. | F12: Tecnología | G12: Q2 | H12: 🔲 Pendiente
A13: 8 | B13: R-08 | C13: Fraude interno en datos financieros | D13: TRANSFERIR + MITIGAR | E13: Separación de funciones y logs de auditoría (mitigar) + póliza de seguro contra fraude interno (transferir). | F13: Administración / Legal | G13: Q3 | H13: 🔲 Pendiente
A14: 9 | B14: R-09 | C14: Pérdida de personal clave | D14: MITIGAR | E14: Planes de sucesión, documentación de conocimiento crítico, proceso formal de offboarding con checklist. | F14: RRHH / CTO | G14: Q3 | H14: 🔲 Pendiente
A15: 10 | B15: R-10 | C15: Robo/pérdida de laptop sin cifrar | D15: MITIGAR | E15: Cifrado de disco obligatorio (BitLocker/FileVault) + gestión remota de dispositivos (MDM). | F15: Tecnología | G15: Q1 | H15: ⚠️ En proceso
A16: 11 | B16: R-11 | C16: Falla de hardware / corte de energía | D16: MITIGAR | E16: UPS + generador de respaldo, mantenimiento preventivo, plan de migración parcial a cloud. | F16: Tecnología | G16: Q3 | H16: 🔲 Pendiente
A17: 12 | B17: R-12 | C17: Fuga de datos personales de empleados | D17: MITIGAR | E17: Clasificación de información, RBAC, auditoría de accesos a sistemas de RRHH. | F17: RRHH / DPO | G17: Q2 | H17: 🔲 Pendiente

Sheet 6-SoA Anexo A
A1: DECLARACIÓN DE APLICABILIDAD (SoA) — Anexo A ISO/IEC 27001:2022
A2: 93 controles en 4 categorías (ISO/IEC 27002:2022) | Seleccionar ¿Aplica? y Madurez — colores automáticos
A3: SoA — Statement of Applicability
A5: # | B5: Control | C5: Nombre del control | D5: Categoría | E5: ¿Aplica? ▼ | F5: Justificación / Riesgo vinculado | G5: Estado de implementación | H5: Madurez ▼
A6: 1 | B6: 5.1 | C6: Políticas de seguridad de la información | D6: Organizacional | E6: Si | H6: No implementado
A7: 2 | B7: 5.2 | C7: Roles y responsabilidades de seguridad de la información | D7: Organizacional | E7: Si | H7: Implementado
A8: 3 | B8: 5.3 | C8: Segregación de funciones | D8: Organizacional | E8: Si | H8: No implementado
A9: 4 | B9: 5.4 | C9: Responsabilidades de gestión | D9: Organizacional | E9: Si | H9: No implementado
A10: 5 | B10: 5.5 | C10: Contacto con autoridades | D10: Organizacional | E10: Si | H10: No implementado
A11: 6 | B11: 5.6 | C11: Contacto con grupos de interés especial | D11: Organizacional | E11: Si | H11: No implementado
A12: 7 | B12: 5.7 | C12: Inteligencia de amenazas | D12: Organizacional | E12: Si | H12: No implementado
A13: 8 | B13: 5.8 | C13: Seguridad de la información en la gestión de proyectos | D13: Organizacional | E13: Si | H13: No implementado
A14: 9 | B14: 5.9 | C14: Inventario de activos de información | D14: Organizacional | E14: Si | H14: No implementado
A15: 10 | B15: 5.10 | C15: Uso aceptable de activos de información | D15: Organizacional | E15: Si | H15: No implementado
A16: 11 | B16: 5.11 | C16: Devolución de activos | D16: Organizacional | E16: Si | H16: No implementado
A17: 12 | B17: 5.12 | C17: Clasificación de la información | D17: Organizacional | E17: Si | H17: No implementado
... A98: 93 | B98: 8.34 | C98: Protección de sistemas de información durante auditorías | D98: Tecnologico | E98: Si | H98: No implementado
B99: Total: 93 controles — 37 Organizacionales · 8 Personas · 14 Físicos · 34 Tecnológicos | Cambiar ¿Aplica? o Madurez actualiza color automáticamente

Sheet 7-Roadmap
A1: ROADMAP DE IMPLEMENTACIÓN — 12 meses hacia ISO 27001:2022
A2: Plan trimestral | Cada hito vinculado a cláusulas y controles del Anexo A
A3: Roadmap
B5: Q1 · Meses 1-3 FUNDAMENTOS | E5: Q2 · Meses 4-6 CONTROLES TÉCNICOS | H5: Q3 · Meses 7-9 MADURACIÓN | K5: Q4 · Meses 10-12 CERTIFICACIÓN
B6: □ Gap analysis completo □ Definir alcance y política SGSI (Cl. 4-5) □ Inventario de activos (A 5.9) □ Clasificación de info (A 5.12) □ MFA en todos los sistemas críticos □ Evaluación de riesgos fase 1 (Cl. 6.1.2) □ Plan de tratamiento aprobado | E6: □ Backups 3-2-1 + prueba restauración (A 8.13) □ RBAC y gestión de accesos (A 5.15-5.18) □ DevSecOps: SAST/DAST en CI/CD (A 8.25-8.29) □ Cifrado datos sensibles (A 8.24) □ DPAs con proveedores cloud (A 5.19-5.23) □ Procedimiento de incidentes (A 5.24-5.28) □ Política de trabajo remoto (A 6.7) | H6: □ Programa concientización anual (A 6.3) □ SIEM y monitoreo centralizado (A 8.16) □ Pentesting externo (A 8.8, 8.29) □ BCP/DRP documentado y probado (A 5.29-5.30) □ Proceso offboarding formal (A 6.5, 5.11) □ Auditoría interna completa (Cl. 9.2) □ No conformidades abiertas | K6: □ Cierre de no conformidades (Cl. 10.1) □ Revisión por la Dirección (Cl. 9.3) □ Actualizar SoA y registros □ Auditoría Stage 1 (documental) □ Auditoría Stage 2 (verificación en campo) □ Resolución de hallazgos de Stage 2 🏆 CERTIFICACIÓN ISO 27001:2022

Sheet 8-Dashboard
A1: DASHBOARD EJECUTIVO — SGSI ISO 27001:2022
A2: Todos los indicadores se recalculan automáticamente al actualizar cualquier hoja del toolkit
B5: =COUNTA('2-Inventario Activos'!C6:C25) -> 20 | D5: =COUNTIF('2-Inventario Activos'!J6:J25,"CRITICO") -> 14 | F5: =COUNTA('4-Matriz Riesgos'!C6:C17) -> 12 | H5: =COUNTIF('4-Matriz Riesgos'!G6:G17,">=16") -> 2 | J5: =COUNTIF('6-SoA Anexo A'!H6:H98,"Implementado y verificado") -> 0 | L5: =COUNTIF('5-Plan Tratamiento'!H6:H17,"*Completado*") -> 1
B6: Activos Inventariados | D6: Activos CRÍTICOS | F6: Riesgos Identificados | H6: Riesgos CRÍTICOS ≥16 | J6: Controles SoA Verificados | L6: Tratamiento Completados
B9: 📊 DISTRIBUCIÓN DE RIESGOS POR NIVEL
B10: Nivel | C10: Cantidad | D10: % del total | E10: Barras
B11: CRITICO | C11: =COUNTIF('4-Matriz Riesgos'!H6:H17,"CRITICO") -> 2 | D11: =C11/12 -> 0.16666667 | E11: =REPT("█",C11*3) -> ██████
B12: ALTO | C12: =COUNTIF('4-Matriz Riesgos'!H6:H17,"ALTO") -> 3 | D12: =C12/12 -> 0.25 | E12: =REPT("█",C12*3) -> █████████
B13: MEDIO | C13: =COUNTIF('4-Matriz Riesgos'!H6:H17,"MEDIO") -> 7 | D13: =C13/12 -> 0.58333333 | E13: =REPT("█",C13*3) -> █████████████████████
B14: BAJO | C14: =COUNTIF('4-Matriz Riesgos'!H6:H17,"BAJO") -> 0 | D14: =C14/12 -> 0 | E14: =REPT("█",C14*3)
B16: 📋 ESTADO CONTROLES SoA POR MADUREZ
B17: Madurez | C17: Cantidad | D17: % del total
B18: No implementado | C18: =COUNTIF('6-SoA Anexo A'!H6:H98,"*No implementado*") -> 92 | D18: =C18/93 -> 0.98924731
B19: En diseño | C19: =COUNTIF('6-SoA Anexo A'!H6:H98,"*En diseño*") -> 0 | D19: =C19/93 -> 0
B20: En implementacion | C20: =COUNTIF('6-SoA Anexo A'!H6:H98,"*En implementacion*") -> 0 | D20: =C20/93 -> 0
B21: Implementado | C21: =COUNTIF('6-SoA Anexo A'!H6:H98,"*Implementado*") -> 93 | D21: =C21/93 -> 1
B22: Implementado y verificado | C22: =COUNTIF('6-SoA Anexo A'!H6:H98,"*Implementado y verificado*") -> 0 | D22: =C22/93 -> 0
B24: 🛡 ESTADO DEL PLAN DE TRATAMIENTO
B25: Estado | C25: Cantidad | D25: % del total
B26: Completado | C26: =COUNTIF('5-Plan Tratamiento'!H6:H17,"*Completado*") -> 1 | D26: =C26/12 -> 0.083333333
B27: En proceso | C27: =COUNTIF('5-Plan Tratamiento'!H6:H17,"*En proceso*") -> 2 | D27: =C27/12 -> 0.16666667
B28: Pendiente | C28: =COUNTIF('5-Plan Tratamiento'!H6:H17,"*Pendiente*") -> 9 | D28: =C28/12 -> 0.75
B30: 🗂 CONTROLES ANEXO A POR CATEGORÍA
B31: Categoría | C31: Total | D31: Si aplica | E31: No implementado
B32: Organizacional | C32: 37 | D32: =COUNTIFS('6-SoA Anexo A'!D6:D98,"Organizacional",'6-SoA Anexo A'!E6:E98,"Si") -> 37 | E32: =COUNTIFS('6-SoA Anexo A'!D6:D98,"Organizacional",'6-SoA Anexo A'!H6:H98,"No implementado") -> 36
B33: Personas | C33: 8 | D33: =COUNTIFS('6-SoA Anexo A'!D6:D98,"Personas",'6-SoA Anexo A'!E6:E98,"Si") -> 8 | E33: =COUNTIFS('6-SoA Anexo A'!D6:D98,"Personas",'6-SoA Anexo A'!H6:H98,"No implementado") -> 8
B34: Fisico | C34: 14 | D34: =COUNTIFS('6-SoA Anexo A'!D6:D98,"Fisico",'6-SoA Anexo A'!E6:E98,"Si") -> 14 | E34: =COUNTIFS('6-SoA Anexo A'!D6:D98,"Fisico",'6-SoA Anexo A'!H6:H98,"No implementado") -> 14
B35: Tecnologico | C35: 34 | D35: =COUNTIFS('6-SoA Anexo A'!D6:D98,"Tecnologico",'6-SoA Anexo A'!E6:E98,"Si") -> 34 | E35: =COUNTIFS('6-SoA Anexo A'!D6:D98,"Tecnologico",'6-SoA Anexo A'!H6:H98,"No implementado") -> 34
