Workbook

Sheet 📋 Instrucciones
A1: ISO 27001:2022 / ISO 31000 — SGSI Toolkit
A2: Conjunto de herramientas de implementación: contexto, activos, riesgos, SoA y plan de tratamiento
A3: ISO/IEC 27001:2022 + ISO 31000:2018 | Instrucciones | Toolkit de Implementación v1.0
B6: 🗂 HOJAS INCLUIDAS EN ESTE TOOLKIT
B7: 1️⃣ Contexto (4.1-4.2) — Factores internos/externos y partes interesadas (cláusula 4 ISO 27001)
B8: 2️⃣ Inventario de Activos — Activos de información, software, hardware, servicios y personas (Anexo A 5.9)
B9: 3️⃣ Identificación de Riesgos — Activo / Amenaza / Vulnerabilidad (metodología ISO 31000)
B10: 4️⃣ Matriz de Evaluación — Probabilidad × Impacto, mapa de calor 5x5, nivel de riesgo
B11: 5️⃣ Plan de Tratamiento — Mitigar / Evitar / Transferir / Aceptar + acciones y responsables
B12: 6️⃣ SoA (Declaración de Aplicabilidad) — Los 93 controles del Anexo A ISO 27001:2022 completos
B13: 7️⃣ Roadmap — Plan de implementación trimestral
B14: 8️⃣ Dashboard — KPIs ejecutivos automáticos
B16: 🎯 METODOLOGÍA APLICADA
B17: • ISO/IEC 27001:2022 — Cláusulas 4 a 10 (requisitos del SGSI) + Anexo A (93 controles, 4 categorías)
B18: • ISO 31000:2018 — Principios, marco de referencia y proceso de gestión de riesgos
... B38: ⚠️ Las celdas en AMARILLO son para completar. El resto se calcula automáticamente.

Sheet 1-Contexto
A1: CONTEXTO DE LA ORGANIZACIÓN — Cláusula 4 ISO 27001:2022
A2: 4.1 Comprensión de la organización y su contexto | 4.2 Partes interesadas | 4.3 Alcance del SGSI
A3: ISO/IEC 27001:2022 + ISO 31000:2018 | Contexto | Toolkit de Implementación v1.0
B5: 4.1 FACTORES INTERNOS
B6: Categoría | C6: Descripción | D6: Impacto en SGSI | E6: Editar ▼
B7: Estructura organizacional | C7: Tamaño, áreas, niveles jerárquicos y modelo de gobierno | D7: Define alcance y roles del SGSI
B8: Cultura organizacional | C8: Nivel de madurez en seguridad, tolerancia al riesgo, agilidad | D8: Condiciona velocidad de adopción de controles
B9: Procesos de negocio | C9: Procesos core, criticidad operativa, dependencias | D9: Determina qué activos/procesos incluir en el alcance
B10: Infraestructura tecnológica | C10: Arquitectura, sistemas legados, nube vs on-premise | D10: Define superficie de ataque y controles técnicos necesarios
B11: Recursos y capacidades | C11: Presupuesto, personal especializado, herramientas disponibles | D11: Limita o habilita el ritmo de implementación
B12: Políticas y objetivos estratégicos | C12: Visión, misión, objetivos de negocio de mediano plazo | D12: El SGSI debe alinearse a objetivos estratégicos
B13: Activos críticos de información | C13: Qué información es vital para la operación y ventaja competitiva | D13: Prioriza foco de protección
B15: 4.1 FACTORES EXTERNOS
B16: Categoría | C16: Descripción | D16: Impacto en SGSI | E16: Editar ▼
B17: Marco legal y regulatorio | C17: Leyes de protección de datos, regulación sectorial, normas locales | D17: Define requisitos legales obligatorios (cláusula 4.2)
B18: Entorno competitivo | C18: Estándares de seguridad exigidos por el mercado y clientes | D18: La certificación puede ser ventaja competitiva o requisito
B19: Amenazas del sector | C19: Tipo de ciberataques frecuentes en la industria (ransomware, phishing, etc.) | D19: Orienta priorización de controles del Anexo A
B20: Cadena de suministro | C20: Dependencia de proveedores tecnológicos críticos (cloud, SaaS) | D20: Requiere gestión de riesgos de terceros (Anexo A 5.19-5.23)
B21: Factores tecnológicos | C21: Tendencias: IA, cloud, trabajo remoto, IoT | D21: Introduce nuevos vectores de riesgo a evaluar
B22: Factores sociopolíticos | C22: Estabilidad regulatoria, relaciones internacionales, geopolítica de datos | D22: Afecta transferencias internacionales y continuidad
B24: 4.2 PARTES INTERESADAS (REQUISITOS Y EXPECTATIVAS)
B25: Parte interesada | C25: Necesidades / Expectativas | D25: Requisito p/SGSI | E25: Editar ▼
B26: Clientes / Usuarios | C26: Confidencialidad, disponibilidad del servicio, cumplimiento normativo | D26: Controles de protección de datos personales
B27: Empleados | C27: Claridad en políticas, protección de sus propios datos, capacitación | D27: Programa de concientización (Anexo A 6.3)
B28: Accionistas / Directorio | C28: Continuidad del negocio, reputación, reducción de riesgo financiero | D28: KPIs de seguridad y reporting periódico
B29: Reguladores / Autoridades | C29: Cumplimiento legal, notificación de incidentes, auditabilidad | D29: Procedimientos documentados y evidencias
B30: Proveedores / Socios | C30: Acuerdos de confidencialidad, gestión de accesos compartidos | D30: Cláusulas contractuales de seguridad (Anexo A 5.20)
B31: Auditores (internos/externos) | C31: Evidencia de controles, trazabilidad, registros | D31: Documentación y registros del SGSI
B33: 4.3 ALCANCE DEL SGSI (declaración a completar)
B34: Completar aquí la declaración formal de alcance: qué procesos, ubicaciones, sistemas y personal están incluidos. Indicar exclusiones justificadas. Ejemplo: 'El SGSI abarca los procesos de [...], los sistemas [...], el personal de las áreas [...] en las ubicaciones [...]. Se excluye [...] por [justificación].'

Sheet 2-Inventario Activos
A1: INVENTARIO DE ACTIVOS — Anexo A 5.9 ISO 27001:2022
A2: Información · Software · Hardware · Servicios · Personas | Valoración CID (Confidencialidad-Integridad-Disponibilidad)
A3: ISO/IEC 27001:2022 + ISO 31000:2018 | Inventario de Activos | Toolkit de Implementación v1.0
A5: # | B5: ID | C5: Activo | D5: Tipo | E5: Propietario | F5: C | G5: I | H5: D | I5: Valor (C+I+D) | J5: Criticidad | K5: Ubicación / Sistema | L5: Estado ▼
A6: 1 | B6: AC-01 | C6: Base de datos de clientes/pacientes | D6: Información | E6: Gerencia Operaciones | F6: 3 | G6: 3 | H6: 3 | I6: =F6+G6+H6 -> 9 | J6: 🔴 CRÍTICO | K6: Servidor / Cloud AWS | L6: Activo
A7: 2 | B7: AC-02 | C7: Datos personales de empleados | D7: Información | E7: RRHH | F7: 3 | G7: 3 | H7: 2 | I7: =F7+G7+H7 -> 8 | J7: 🔴 CRÍTICO | K7: Sistema RRHH / HRIS | L7: Activo
A8: 3 | B8: AC-03 | C8: Código fuente de aplicaciones | D8: Información / Software | E8: Tecnología | F8: 3 | G8: 3 | H8: 2 | I8: =F8+G8+H8 -> 8 | J8: 🔴 CRÍTICO | K8: GitHub / GitLab | L8: Activo
A9: 4 | B9: AC-04 | C9: Contratos y documentación legal | D9: Información | E9: Legal / Administración | F9: 3 | G9: 3 | H9: 2 | I9: =F9+G9+H9 -> 8 | J9: 🔴 CRÍTICO | K9: Repositorio documental | L9: Activo
A10: 5 | B10: AC-05 | C10: Registros financieros y facturación | D10: Información | E10: Administración | F10: 3 | G10: 3 | H10: 2 | I10: =F10+G10+H10 -> 8 | J10: 🔴 CRÍTICO | K10: ERP / Sistema contable | L10: Activo
A11: 6 | B11: AC-06 | C11: Aplicación web principal | D11: Software | E11: Tecnología | F11: 2 | G11: 3 | H11: 3 | I11: =F11+G11+H11 -> 8 | J11: 🔴 CRÍTICO | K11: AWS — Producción | L11: Activo
A12: 7 | B12: AC-07 | C12: Aplicación móvil | D12: Software | E12: Tecnología | F12: 2 | G12: 3 | H12: 3 | I12: =F12+G12+H12 -> 8 | J12: 🔴 CRÍTICO | K12: App Store / Play Store | L12: Activo
A13: 8 | B13: AC-08 | C13: Sistema CRM | D13: Software | E13: Comercial | F13: 2 | G13: 2 | H13: 2 | I13: =F13+G13+H13 -> 6 | J13: 🟡 IMPORTANTE | K13: Cloud SaaS | L13: Activo
A14: 9 | B14: AC-09 | C14: Sistema de mesa de ayuda (ticketing) | D14: Software | E14: Atención al Cliente | F14: 2 | G14: 2 | H14: 2 | I14: =F14+G14+H14 -> 6 | J14: 🟡 IMPORTANTE | K14: Cloud SaaS | L14: Activo
A15: 10 | B15: AC-10 | C15: Suite de productividad (Google/M365) | D15: Software / Servicio | E15: Tecnología | F15: 3 | G15: 2 | H15: 3 | I15: =F15+G15+H15 -> 8 | J15: 🔴 CRÍTICO | K15: Cloud | L15: Activo
A16: 11 | B16: AC-11 | C16: Laptops corporativas | D16: Hardware | E16: Tecnología / RRHH | F16: 3 | G16: 2 | H16: 2 | I16: =F16+G16+H16 -> 7 | J16: 🟡 IMPORTANTE | K16: Equipos asignados a empleados | L16: Activo
A17: 12 | B17: AC-12 | C17: Servidores / infraestructura on-premise | D17: Hardware | E17: Tecnología | F17: 3 | G17: 3 | H17: 3 | I17: =F17+G17+H17 -> 9 | J17: 🔴 CRÍTICO | K17: Datacenter / Oficina | L17: Activo
... A25: 20 | B25: AC-20 | C25: Personal con acceso a datos sensibles | D25: Personas | E25: Áreas operativas | F25: 3 | G25: 3 | H25: 2 | I25: =F25+G25+H25 -> 8 | J25: 🔴 CRÍTICO | K25: Interno | L25: Activo
B27: 📐 Escala C/I/D: 1=Bajo 2=Medio 3=Alto | Valor = C+I+D (máx 9) | Crítico ≥8 · Importante 6-7 · Normal ≤5 | Columnas C/I/D y Estado son editables (amarillo)

Sheet 3-Identif Riesgos
A1: IDENTIFICACIÓN DE RIESGOS — Activo / Amenaza / Vulnerabilidad
A2: Proceso de identificación según ISO 31000 §6.4.2 y ISO/IEC 27005 | Foco en activos críticos del inventario
A3: ISO/IEC 27001:2022 + ISO 31000:2018 | Identificación de Riesgos | Toolkit de Implementación v1.0
A5: # | B5: ID | C5: Activo crítico | D5: Amenaza | E5: Vulnerabilidad | F5: Origen ▼
A6: 1 | B6: R-01 | C6: Base de datos de clientes/pacientes | D6: Acceso no autorizado / exfiltración de datos | E6: MFA no implementado universalmente; gestión de accesos informal | F6: Externo
A7: 2 | B7: R-02 | C7: Infraestructura cloud (AWS/Azure) | D7: Ransomware con cifrado de datos y caída de servicio | E7: Backups sin pruebas de restauración regulares; sin plan de continuidad | F7: Externo
A8: 3 | B8: R-03 | C8: Suite de productividad (correo) | D8: Phishing / Business Email Compromise (BEC) | E8: Capacitación en seguridad esporádica; sin filtros DMARC/DKIM/SPF | F8: Externo
A9: 4 | B9: R-04 | C9: Aplicación web principal | D9: Inyección SQL / XSS / explotación OWASP Top 10 | E9: Sin revisiones de seguridad de código (SAST/DAST) en el ciclo de desarrollo | F9: Externo
A10: 5 | B10: R-05 | C10: Código fuente (repositorios) | D10: Robo o manipulación de código / inyección de malware | E10: Gestión de accesos sin revisión periódica; sin ramas protegidas | F10: Interno/Externo
A11: 6 | B11: R-06 | C11: Aplicación móvil | D11: Robo de credenciales / sesión no autorizada | E11: Sin MFA en la app; tokens de sesión con vida útil extendida | F11: Externo
A12: 7 | B12: R-07 | C12: Conectividad VPN / acceso remoto | D12: Interceptación de comunicaciones (Man-in-the-Middle) | E12: Sin política de acceso remoto formal; dispositivos BYOD sin control | F12: Externo
A13: 8 | B13: R-08 | C13: Registros financieros y facturación | D13: Fraude interno / manipulación de datos financieros | E13: Sin separación de funciones; sin auditoría de accesos | F13: Interno
A14: 9 | B14: R-09 | C14: Equipo de Tecnología / personal clave | D14: Pérdida de personal clave / fuga de conocimiento crítico | E14: Sin gestión de conocimiento documentada; sin proceso de offboarding formal | F14: Interno
A15: 10 | B15: R-10 | C15: Laptops corporativas | D15: Robo o pérdida de equipo con datos sin cifrar | E15: Sin cifrado de disco obligatorio; sin gestión remota de dispositivos (MDM) | F15: Externo
A16: 11 | B16: R-11 | C16: Servidores on-premise | D16: Falla de hardware / corte de energía prolongado | E16: Sin redundancia (UPS/generador); sin contrato de mantenimiento preventivo | F16: Ambiental
A17: 12 | B17: R-12 | C17: Datos personales de empleados | D17: Fuga de datos personales y laborales sensibles | E17: Sin clasificación de la información; controles de acceso deficientes | F17: Interno

Sheet 4-Matriz Riesgos
A1: MATRIZ DE EVALUACIÓN DE RIESGOS — Probabilidad × Impacto
A2: Análisis y evaluación de riesgos según ISO 31000 §6.4.3-6.4.4 | Escala 5x5 (1-25)
A3: ISO/IEC 27001:2022 + ISO 31000:2018 | Matriz de Evaluación | Toolkit de Implementación v1.0
A5: # | B5: ID | C5: Riesgo | D5: Activo afectado | E5: Probab. (1-5) | F5: Impacto (1-5) | G5: Nivel (P×I) | H5: Categoría | I5: Riesgo residual obj. | J5: Prioridad
A6: 1 | B6: R-01 | C6: Exfiltración de datos por acceso no autorizado a BD crítica | D6: BD clientes/pacientes | E6: 4 | F6: 5 | G6: =E6*F6 -> 20 | H6: CRÍTICO | I6: ≤ 8 (Medio-Bajo) | J6: 1°
A7: 2 | B7: R-02 | C7: Ransomware con cifrado de datos en infraestructura cloud | D7: Infraestructura cloud | E7: 4 | F7: 5 | G7: =E7*F7 -> 20 | H7: CRÍTICO | I7: ≤ 8 (Medio-Bajo) | J7: 1°
A8: 3 | B8: R-03 | C8: Compromiso de cuenta corporativa por phishing/BEC | D8: Correo corporativo | E8: 4 | F8: 4 | G8: =E8*F8 -> 16 | H8: CRÍTICO | I8: ≤ 8 (Medio-Bajo) | J8: 1°
A9: 4 | B9: R-04 | C9: Inyección SQL/XSS explotando vulnerabilidades web | D9: App web principal | E9: 3 | F9: 4 | G9: =E9*F9 -> 12 | H9: ALTO | I9: ≤ 8 (Medio-Bajo) | J9: 2°
A10: 5 | B10: R-05 | C10: Robo/manipulación de código fuente con inyección de malware | D10: Repositorios de código | E10: 2 | F10: 4 | G10: =E10*F10 -> 8 | H10: MEDIO | I10: ≤ 8 (Medio-Bajo) | J10: 3°
A11: 6 | B11: R-06 | C11: Robo de credenciales en app móvil sin MFA | D11: App móvil | E11: 3 | F11: 4 | G11: =E11*F11 -> 12 | H11: ALTO | I11: ≤ 8 (Medio-Bajo) | J11: 2°
A12: 7 | B12: R-07 | C12: Interceptación de comunicaciones vía VPN mal configurada | D12: VPN / acceso remoto | E12: 3 | F12: 3 | G12: =E12*F12 -> 9 | H12: MEDIO | I12: ≤ 8 (Medio-Bajo) | J12: 3°
A13: 8 | B13: R-08 | C13: Fraude interno sobre datos financieros sin controles | D13: Registros financieros | E13: 2 | F13: 4 | G13: =E13*F13 -> 8 | H13: MEDIO | I13: ≤ 8 (Medio-Bajo) | J13: 3°
A14: 9 | B14: R-09 | C14: Pérdida de personal clave sin transferencia de conocimiento | D14: Equipo Tecnología | E14: 3 | F14: 3 | G14: =E14*F14 -> 9 | H14: MEDIO | I14: ≤ 8 (Medio-Bajo) | J14: 3°
A15: 10 | B15: R-10 | C15: Robo o pérdida de laptop corporativa sin cifrado | D15: Laptops corporativas | E15: 3 | F15: 3 | G15: =E15*F15 -> 9 | H15: MEDIO | I15: ≤ 8 (Medio-Bajo) | J15: 3°
A16: 11 | B16: R-11 | C16: Falla de hardware / corte prolongado de energía | D16: Servidores on-premise | E16: 2 | F16: 3 | G16: =E16*F16 -> 6 | H16: MEDIO | I16: ≤ 8 (Medio-Bajo) | J16: 3°
A17: 12 | B17: R-12 | C17: Fuga de datos personales de empleados | D17: Datos personales empleados | E17: 3 | F17: 4 | G17: =E17*F17 -> 12 | H17: ALTO | I17: ≤ 8 (Medio-Bajo) | J17: 2°
B21: 🗺 MAPA DE CALOR — Matriz 5×5
B22: Impacto ▼ / Prob. ► | C22: 1 | D22: 2 | E22: 3 | F22: 4 | G22: 5
B23: 5 | C23: 5 | D23: 10 | E23: 15 | F23: 20 | G23: 25
B24: 4 | C24: 4 | D24: 8 | E24: 12 | F24: 16 | G24: 20
B25: 3 | C25: 3 | D25: 6 | E25: 9 | F25: 12 | G25: 15
B26: 2 | C26: 2 | D26: 4 | E26: 6 | F26: 8 | G26: 10
B27: 1 | C27: 1 | D27: 2 | E27: 3 | F27: 4 | G27: 5
B29: Bajo (1-5) | D29: Medio (6-10) | F29: Alto (11-15) | H29: Crítico (16-25)

Sheet 5-Plan Tratamiento
A1: PLAN DE TRATAMIENTO DE RIESGOS
A2: ISO 31000 §6.5 | Opciones: Mitigar · Evitar · Transferir · Aceptar
A3: ISO/IEC 27001:2022 + ISO 31000:2018 | Plan de Tratamiento | Toolkit de Implementación v1.0
A5: # | B5: ID | C5: Riesgo | D5: Tratamiento ▼ | E5: Acción / Justificación | F5: Responsable | G5: Fecha objetivo | H5: Estado ▼
A6: 1 | B6: R-01 | C6: Exfiltración de datos por acceso no autorizado | D6: MITIGAR | E6: Implementar MFA obligatorio, RBAC, cifrado en reposo/tránsito. Riesgo crítico — requiere reducción activa. | F6: CISO / Tecnología | G6: Q1 | H6: 🔲 Pendiente
A7: 2 | B7: R-02 | C7: Ransomware en infraestructura cloud | D7: MITIGAR | E7: Política de backups 3-2-1 con pruebas de restauración periódicas + segmentación de red + BCP. | F7: Tecnología | G7: Q1 | H7: 🔲 Pendiente
A8: 3 | B8: R-03 | C8: Compromiso de cuenta por phishing/BEC | D8: MITIGAR | E8: MFA en correo, DMARC/DKIM/SPF, simulaciones de phishing y capacitación continua. | F8: CISO / RRHH | G8: Q1 | H8: 🔲 Pendiente
A9: 4 | B9: R-04 | C9: Inyección SQL/XSS en app web | D9: MITIGAR | E9: SAST/DAST en CI/CD, estándar OWASP ASVS, pentesting anual. | F9: Tecnología | G9: Q2 | H9: 🔲 Pendiente
A10: 5 | B10: R-05 | C10: Robo de código fuente / malware en repositorio | D10: MITIGAR | E10: Ramas protegidas, revisión obligatoria de PR, escaneo de dependencias (SCA), MFA en GitHub/GitLab. | F10: Tecnología | G10: Q2 | H10: 🔲 Pendiente
A11: 6 | B11: R-06 | C11: Robo de credenciales en app móvil | D11: MITIGAR | E11: MFA en la app, expiración de tokens reducida, detección de anomalías. | F11: Tecnología | G11: Q2 | H11: 🔲 Pendiente
A12: 7 | B12: R-07 | C12: Interceptación de comunicaciones VPN | D12: MITIGAR | E12: Política formal de acceso remoto, VPN corporativa cifrada, evaluar modelo Zero Trust. | F12: Tecnología | G12: Q2 | H12: 🔲 Pendiente
A13: 8 | B13: R-08 | C13: Fraude interno en datos financieros | D13: TRANSFERIR + MITIGAR | E13: Separación de funciones, logs de auditoría (mitigar) + póliza de seguro contra fraude (transferir). | F13: Administración / Legal | G13: Q3 | H13: 🔲 Pendiente
A14: 9 | B14: R-09 | C14: Pérdida de personal clave | D14: MITIGAR | E14: Planes de sucesión, documentación de conocimiento crítico, proceso formal de offboarding. | F14: RRHH / CTO | G14: Q3 | H14: 🔲 Pendiente
A15: 10 | B15: R-10 | C15: Robo/pérdida de laptop sin cifrar | D15: MITIGAR | E15: Cifrado de disco obligatorio (BitLocker/FileVault), gestión remota de dispositivos (MDM). | F15: Tecnología | G15: Q1 | H15: 🔲 Pendiente
A16: 11 | B16: R-11 | C16: Falla de hardware / corte de energía | D16: MITIGAR | E16: UPS + generador de respaldo, contrato de mantenimiento preventivo, plan de migración a cloud. | F16: Tecnología | G16: Q3 | H16: 🔲 Pendiente
A17: 12 | B17: R-12 | C17: Fuga de datos personales de empleados | D17: MITIGAR | E17: Clasificación de información, RBAC, auditoría de accesos a sistemas de RRHH. | F17: RRHH / DPO | G17: Q2 | H17: 🔲 Pendiente

Sheet 6-SoA Anexo A
A1: DECLARACIÓN DE APLICABILIDAD (SoA) — Anexo A completo
A2: Los 93 controles de ISO/IEC 27001:2022 (basados en ISO/IEC 27002:2022) en sus 4 categorías
A3: ISO/IEC 27001:2022 + ISO 31000:2018 | SoA — Statement of Applicability | Toolkit de Implementación v1.0
A5: # | B5: Control | C5: Nombre | D5: Categoría | E5: ¿Aplica? ▼ | F5: Justificación / Riesgo vinculado | G5: Estado implementación | H5: Madurez ▼
A6: 1 | B6: 5.1 | C6: Políticas de seguridad de la información | D6: Organizacional | E6: Sí | H6: No implementado
A7: 2 | B7: 5.2 | C7: Roles y responsabilidades de seguridad | D7: Organizacional | E7: Sí | H7: No implementado
A8: 3 | B8: 5.3 | C8: Segregación de funciones | D8: Organizacional | E8: Sí | H8: No implementado
A9: 4 | B9: 5.4 | C9: Responsabilidades de gestión | D9: Organizacional | E9: Sí | H9: No implementado
A10: 5 | B10: 5.5 | C10: Contacto con autoridades | D10: Organizacional | E10: Sí | H10: No implementado
A11: 6 | B11: 5.6 | C11: Contacto con grupos de interés especial | D11: Organizacional | E11: Sí | H11: No implementado
A12: 7 | B12: 5.7 | C12: Inteligencia de amenazas | D12: Organizacional | E12: Sí | H12: No implementado
A13: 8 | B13: 5.8 | C13: Seguridad en gestión de proyectos | D13: Organizacional | E13: Sí | H13: No implementado
A14: 9 | B14: 5.9 | C14: Inventario de activos de información | D14: Organizacional | E14: Sí | H14: No implementado
A15: 10 | B15: 5.10 | C15: Uso aceptable de activos | D15: Organizacional | E15: Sí | H15: No implementado
A16: 11 | B16: 5.11 | C16: Devolución de activos | D16: Organizacional | E16: Sí | H16: No implementado
A17: 12 | B17: 5.12 | C17: Clasificación de la información | D17: Organizacional | E17: Sí | H17: No implementado
... A98: 93 | B98: 8.34 | C98: Protección de sistemas durante auditorías | D98: Tecnológico | E98: Sí | H98: No implementado
B100: Total de controles del Anexo A 2022: 93 (37 Organizacionales · 8 Personas · 14 Físicos · 34 Tecnológicos) — completar columnas E,F,G,H

Sheet 7-Roadmap
A1: ROADMAP DE IMPLEMENTACIÓN — 12 meses
A2: Plan trimestral hacia la certificación ISO/IEC 27001:2022
A3: ISO/IEC 27001:2022 + ISO 31000:2018 | Roadmap | Toolkit de Implementación v1.0
B5: Q1 (Meses 1-3) FUNDAMENTOS | E5: Q2 (Meses 4-6) CONTROLES TÉCNICOS | H5: Q3 (Meses 7-9) MADURACIÓN | K5: Q4 (Meses 10-12) CERTIFICACIÓN
B6: • Gap analysis inicial • Definir alcance y política SGSI • Inventario de activos • MFA en sistemas críticos • Evaluación de riesgos fase 1 | E6: • Backups + pruebas restauración • RBAC y gestión de accesos • DevSecOps (SAST/DAST) • Cifrado de datos sensibles • Gestión de proveedores | H6: • Programa de concientización • SIEM y monitoreo • Pentesting externo • Plan de continuidad (BCP) • Auditoría interna | K6: • Cierre de no conformidades • Revisión por la Dirección • Actualizar SoA y documentación • Auditoría Stage 1 • Auditoría Stage 2 → CERTIFICACIÓN

Sheet 8-Dashboard
A1: DASHBOARD EJECUTIVO — SGSI ISO 27001:2022
A2: Indicadores actualizados automáticamente desde las hojas de Activos, Riesgos y SoA
A3: ISO/IEC 27001:2022 + ISO 31000:2018 | Dashboard | Toolkit de Implementación v1.0
B6: =COUNTA('2-Inventario Activos'!C6:C25) -> 20 | D6: =COUNTIF('2-Inventario Activos'!J6:J25,"🔴 CRÍTICO") -> 15 | F6: =COUNTA('4-Matriz Riesgos'!C6:C17) -> 12 | H6: =COUNTIF('4-Matriz Riesgos'!G6:G17,">=16") -> 3 | J6: =COUNTIF('6-SoA Anexo A'!H6:H98,"Implementado y verificado") -> 0 | L6: =93 -> 93
B7: Activos Inventariados | D7: Activos Críticos | F7: Riesgos Identificados | H7: Riesgos Críticos (≥16) | J7: Controles SoA Implementados | L7: Total Controles Anexo A
B9: 📊 DISTRIBUCIÓN DE RIESGOS POR NIVEL
B10: Nivel | C10: Cantidad | D10: %
B11: CRÍTICO | C11: =COUNTIF('4-Matriz Riesgos'!H6:H17,"CRÍTICO") -> 3 | D11: =C11/12 -> 0.25
B12: ALTO | C12: =COUNTIF('4-Matriz Riesgos'!H6:H17,"ALTO") -> 3 | D12: =C12/12 -> 0.25
B13: MEDIO | C13: =COUNTIF('4-Matriz Riesgos'!H6:H17,"MEDIO") -> 6 | D13: =C13/12 -> 0.5
B14: BAJO | C14: =COUNTIF('4-Matriz Riesgos'!H6:H17,"BAJO") -> 0 | D14: =C14/12 -> 0
B16: 🗂 CONTROLES DEL ANEXO A POR CATEGORÍA
B17: Categoría | C17: Total controles
B18: Organizacional | C18: 37
B19: Personas | C19: 8
B20: Físico | C20: 14
B21: Tecnológico | C21: 34
